redbreast/__init__.py
redbreast/querylist.py
redbreast/testing.py
redbreast-1.1.5.dist-info/LICENSE
redbreast-1.1.5.dist-info/METADATA
redbreast-1.1.5.dist-info/WHEEL
redbreast-1.1.5.dist-info/top_level.txt
redbreast-1.1.5.dist-info/RECORD
